{"cameraMode":{"drawMode":0,"name":"Shaded","section":"Shading Mode"},"sceneLighting":false,"audioPlay":false,"sceneViewState":{"m_AlwaysRefresh":false,"showFog":true,"showSkybox":false,"showFlares":true,"showImageEffects":true,"showParticleSystems":true,"showVisualEffectGraphs":true,"m_FxEnabled":true},"in2DMode":false,"pivot":{"x":6.148374557495117,"y":3.4875688552856447,"z":2.1682751178741457},"rotation":{"x":0.011183605529367924,"y":-0.9801981449127197,"z":0.18901944160461427,"w":0.05798952654004097},"size":16.01381492614746,"orthographic":false}